{
  "users": [
    {
      "id": 3,
      "name": "NICOLEA LATIMER",
      "email": "nlatimer2@ucoz.ru",
      "address": "91221 Esker Trail"
    },
    {
      "id": 7,
      "name": "FLETCHER NELTHORP",
      "email": "fnelthorp6@jiathis.com",
      "address": " Tban Plaza"
    },
    {
      "id": 10,
      "name": "AUDRE MACCUMISKEY",
      "email": "amaccumiskey9@wsj.com",
      "address": "774 Coolidge Alley"
    },
    {
      "id": 11,
      "name": "MILZIE CORBALLY",
      "email": "mcorballya@globo.com",
      "address": "45 Parkside Alley"
    },
    {
      "id": 12,
      "name": "GIPSY HIORN",
      "email": "ghiornb@livejournal.com",
      "address": "24 Golf Course Avenue"
    },
    {
      "id": 13,
      "name": "ALLARD SATFORD",
      "email": "asatfordc@clickbank.net",
      "address": "4 Bartillon Junction"
    },
    {
      "id": 14,
      "name": "DANNEL WALSH",
      "email": "dwalshd@bravesites.com",
      "address": "5708 Pierstorff Court"
    },
    {
      "id": 15,
      "name": "FAIR MARSHLAND",
      "email": "fmarshlande@usnews.com",
      "address": "3804 Green Junction"
    },
    {
      "id": 16,
      "name": "BECKA CASSIDY",
      "email": "bcassidyf@rediff.com",
      "address": "6219 Anzinger Alley"
    },
    {
      "id": 17,
      "name": "FELICIO GIDMAN",
      "email": "fgidmang@bloglovin.com",
      "address": "23309 Fair Oaks Plaza"
    },
    {
      "id": 18,
      "name": "MARTIN DOTSON",
      "email": "mdotsonh@linkedin.com",
      "address": "596 Fordem Park"
    },
    {
      "id": 19,
      "name": "KYLEN DARKO",
      "email": "kdarkoi@bloomberg.com",
      "address": "9448 Melody Crossing"
    },
    {
      "id": 20,
      "name": "ORSOLA ATHERSMITH",
      "email": "oathersmithj@mashable.com",
      "address": "3021 Evergreen Hill"
    },
    {
      "id": 21,
      "name": "ALVIE ALLENDER",
      "email": "aallenderk@nydailynews.com",
      "address": "54155 Dahle Crossing"
    },
    {
      "id": 22,
      "name": "LOLLY CHRISTIENSEN",
      "email": "lchristiensenl@addtoany.com",
      "address": "2 Saint Paul Plaza"
    },
    {
      "id": 23,
      "name": "ADRIA SKELLEN",
      "email": "askellenm@nifty.com",
      "address": "24 Division Lane"
    },
    {
      "id": 24,
      "name": "ALESSANDRO GOOK",
      "email": "agookn@parallels.com",
      "address": "82 Glacier Hill Street"
    },
    {
      "id": 25,
      "name": "MANUEL RAKE",
      "email": "mrakeo@timesonline.co.uk",
      "address": "1478 Toban Avenue"
    },
    {
      "id": 26,
      "name": "NEELY RIGARD",
      "email": "nrigardp@va.gov",
      "address": "3 Havey Trail"
    },
    {
      "id": 27,
      "name": "NOBIE YAKOV",
      "email": "nyakovq@huffingtonpost.com",
      "address": "66 Knutson Pass"
    },
    {
      "id": 28,
      "name": "ROLLINS FREDDI",
      "email": "rfreddir@trellian.com",
      "address": "08788 Kenwood Crossing"
    },
    {
      "id": 29,
      "name": "FLORRI DEEM",
      "email": "fdeems@gmpg.org",
      "address": "79066 Walton Road"
    },
    {
      "id": 30,
      "name": "HELAINE LENARD",
      "email": "hlenardt@unblog.fr",
      "address": "8165 Norway Maple Point"
    },
    {
      "id": 31,
      "name": "COLAS TUFFELL",
      "email": "ctuffellu@cnbc.com",
      "address": "5900 Hoffman Plaza"
    },
    {
      "id": 32,
      "name": "KARL GREW",
      "email": "kgrewv@amazonaws.com",
      "address": "0645 Lyons Street"
    },
    {
      "id": 33,
      "name": "ANDREA WILLBRAHAM",
      "email": "awillbrahamw@unesco.org",
      "address": "77542 Southridge Circle"
    },
    {
      "id": 34,
      "name": "ALAMEDA CAWKWELL",
      "email": "acawkwellx@eventbrite.com",
      "address": "726 Weeping Birch Avenue"
    },
    {
      "id": 35,
      "name": "CORBIE SUMSHON",
      "email": "csumshony@exblog.jp",
      "address": "18 Heath Junction"
    },
    {
      "id": 36,
      "name": "FILBERT EASUM",
      "email": "feasumz@abc.net.au",
      "address": "592 Maryland Hill"
    },
    {
      "id": 37,
      "name": "DAISIE BIRMINGHAM",
      "email": "dbirmingham10@so-net.ne.jp",
      "address": "64510 Caliangt Lane"
    },
    {
      "id": 38,
      "name": "BIRD LIVEROCK",
      "email": "bliverock11@sina.com.cn",
      "address": "8 Kensington Street"
    },
    {
      "id": 39,
      "name": "WINIFIELD ARRIGHI",
      "email": "warrighi12@dot.gov",
      "address": "859 School Hill"
    },
    {
      "id": 40,
      "name": "GODWIN CONNELL",
      "email": "gconnell13@ft.com",
      "address": "32630 Sachs Road"
    },
    {
      "id": 41,
      "name": "GABBEY WATERDRINKER",
      "email": "gwaterdrinker14@booking.com",
      "address": "5083 Anniversary Avenue"
    },
    {
      "id": 42,
      "name": "RAVID WILFLINGER",
      "email": "rwilflinger15@devhub.com",
      "address": "5926 Karstens Drive"
    },
    {
      "id": 43,
      "name": "AUGUSTINE KERNAN",
      "email": "akernan16@cloudflare.com",
      "address": "9 Clove Pass"
    },
    {
      "id": 44,
      "name": "NICKOLAS LORENZ",
      "email": "nlorenz17@hibu.com",
      "address": "7936 Luster Point"
    },
    {
      "id": 45,
      "name": "DION HAIN",
      "email": "dhain18@cisco.com",
      "address": "187 Buena Vista Street"
    },
    {
      "id": 46,
      "name": "ALEX APHALE",
      "email": "aaphale19@fotki.com",
      "address": "61010 Claremont Street"
    },
    {
      "id": 47,
      "name": "DEV GEROLDO",
      "email": "dgeroldo1a@addtoany.com",
      "address": "76 Sunnyside Alley"
    },
    {
      "id": 48,
      "name": "JANDY O'HDIRSCOLL",
      "email": "johdirscoll1b@twitpic.com",
      "address": "0 Elmside Court"
    },
    {
      "id": 49,
      "name": "VIVIANNA LENARD",
      "email": "vlenard1c@businesswire.com",
      "address": "3 Hudson Pass"
    },
    {
      "id": 50,
      "name": "LAZAR DOWNE",
      "email": "ldowne1d@bbc.co.uk",
      "address": "39165 High Crossing Avenue"
    },
    {
      "id": 51,
      "name": "THEODORA IDDISON",
      "email": "tiddison1e@scribd.com",
      "address": "34485 Crest Line Crossing"
    },
    {
      "id": 52,
      "name": "ELWIRA BEESWING",
      "email": "ebeeswing1f@ehow.com",
      "address": "144 Utah Avenue"
    },
    {
      "id": 53,
      "name": "ADRIANNA KERTESS",
      "email": "akertess1g@phpbb.com",
      "address": "405 Coolidge Way"
    },
    {
      "id": 54,
      "name": "FREIDA MATHERS",
      "email": "fmathers1h@ftc.gov",
      "address": "974 Prairie Rose Junction"
    },
    {
      "id": 55,
      "name": "ANNA-DIANA MCGOWRAN",
      "email": "amcgowran1i@ft.com",
      "address": "2 Shopko Circle"
    },
    {
      "id": 56,
      "name": "ESSIE MAZDON",
      "email": "emazdon1j@springer.com",
      "address": "40 Thierer Lane"
    },
    {
      "id": 57,
      "name": "ANTON MCALINION",
      "email": "amcalinion1k@pen.io",
      "address": "9461 Maryland Place"
    },
    {
      "id": 58,
      "name": "DAG DOLAN",
      "email": "ddolan1l@clickbank.net",
      "address": "1959 Tennyson Lane"
    },
    {
      "id": 59,
      "name": "SAVINA KENNARD",
      "email": "skennard1m@ucoz.com",
      "address": "3367 Kim Parkway"
    },
    {
      "id": 60,
      "name": "CHUCHO TRIMMING",
      "email": "ctrimming1n@webnode.com",
      "address": "606 Anderson Plaza"
    },
    {
      "id": 61,
      "name": "ABBY TUNNA",
      "email": "atunna1o@newyorker.com",
      "address": "67 Jay Way"
    },
    {
      "id": 62,
      "name": "DANNIE ROMAN",
      "email": "droman1p@guardian.co.uk",
      "address": "20 Karstens Way"
    },
    {
      "id": 63,
      "name": "GEARARD FREDA",
      "email": "gfreda1q@amazon.de",
      "address": "02187 International Parkway"
    },
    {
      "id": 64,
      "name": "DENNA ULLYATT",
      "email": "dullyatt1r@diigo.com",
      "address": "95000 Butternut Junction"
    },
    {
      "id": 65,
      "name": "AMBUR GIROLDO",
      "email": "agiroldo1s@reference.com",
      "address": "29 Bartillon Plaza"
    },
    {
      "id": 66,
      "name": "ELENORE WESTWOOD",
      "email": "ewestwood1t@wufoo.com",
      "address": "3 West Way"
    },
    {
      "id": 67,
      "name": "LUCRETIA BUTTERIS",
      "email": "lbutteris1u@biblegateway.com",
      "address": "905 Ilene Road"
    },
    {
      "id": 68,
      "name": "FORESTER DREWSON",
      "email": "fdrewson1v@time.com",
      "address": "3556 Artisan Hill"
    },
    {
      "id": 69,
      "name": "CARON NUSSEY",
      "email": "cnussey1w@wikipedia.org",
      "address": "0382 Luster Avenue"
    },
    {
      "id": 70,
      "name": "NOVELIA PATERNOSTER",
      "email": "npaternoster1x@un.org",
      "address": "59 Linden Way"
    },
    {
      "id": 71,
      "name": "TEDD CASSEDY",
      "email": "tcassedy1y@jugem.jp",
      "address": "25 Harbort Pass"
    },
    {
      "id": 72,
      "name": "PHILIPPE LONGBONE",
      "email": "plongbone1z@posterous.com",
      "address": "55 Center Street"
    },
    {
      "id": 73,
      "name": "ALYSS LOUGHLAN",
      "email": "aloughlan20@over-blog.com",
      "address": "87652 Vermont Plaza"
    },
    {
      "id": 74,
      "name": "CARA FEETHAM",
      "email": "cfeetham21@so-net.ne.jp",
      "address": "68112 Lawn Circle"
    },
    {
      "id": 75,
      "name": "ANDROMACHE BOTTE",
      "email": "abotte22@ezinearticles.com",
      "address": "35748 Schurz Court"
    },
    {
      "id": 76,
      "name": "HAILY ODNEY",
      "email": "hodney23@sbwire.com",
      "address": "0563 Melvin Lane"
    },
    {
      "id": 77,
      "name": "SILEAS SONGER",
      "email": "ssonger24@globo.com",
      "address": "794 Westridge Plaza"
    },
    {
      "id": 78,
      "name": "GINA BIERS",
      "email": "gbiers25@reverbnation.com",
      "address": "1 Northland Drive"
    },
    {
      "id": 79,
      "name": "ALDRICH PLEVEY",
      "email": "aplevey26@blinklist.com",
      "address": "47076 5th Drive"
    },
    {
      "id": 80,
      "name": "SONNIE SACKER",
      "email": "ssacker27@pinterest.com",
      "address": "675 Moland Way"
    },
    {
      "id": 81,
      "name": "CHARLA GEBBY",
      "email": "cgebby28@domainmarket.com",
      "address": "925 Warrior Parkway"
    },
    {
      "id": 82,
      "name": "DASYA MAMMATT",
      "email": "dmammatt29@google.com.br",
      "address": "83297 Hauk Circle"
    },
    {
      "id": 83,
      "name": "LAURA JONK",
      "email": "ljonk2a@utexas.edu",
      "address": "36230 Dexter Pass"
    },
    {
      "id": 84,
      "name": "MAISIE BECHE",
      "email": "mbeche2b@imdb.com",
      "address": "045 Del Sol Trail"
    },
    {
      "id": 85,
      "name": "HUMFREY ESMONDE",
      "email": "hesmonde2c@cdc.gov",
      "address": "3409 Jenifer Alley"
    },
    {
      "id": 86,
      "name": "OBEDIAH JULYAN",
      "email": "ojulyan2d@google.com.br",
      "address": "4 Banding Lane"
    },
    {
      "id": 87,
      "name": "DONETTA GLANERT",
      "email": "dglanert2e@usgs.gov",
      "address": "4 Tennessee Hill"
    },
    {
      "id": 88,
      "name": "GWENDOLIN NEWLIN",
      "email": "gnewlin2f@prlog.org",
      "address": "41 West Circle"
    },
    {
      "id": 89,
      "name": "ASHLI PICKAVER",
      "email": "apickaver2g@virginia.edu",
      "address": "39588 Dunning Circle"
    },
    {
      "id": 90,
      "name": "BENEDICK MANKTELOW",
      "email": "bmanktelow2h@cmu.edu",
      "address": "3 2nd Place"
    },
    {
      "id": 91,
      "name": "CAROLIN QUARLES",
      "email": "cquarles2i@clickbank.net",
      "address": "03030 Porter Crossing"
    },
    {
      "id": 92,
      "name": "TYBALT DELACOURT",
      "email": "tdelacourt2j@unblog.fr",
      "address": "088 Rowland Hill"
    },
    {
      "id": 93,
      "name": "SHELBY KOVACS",
      "email": "skovacs2k@angelfire.com",
      "address": "05 Macpherson Drive"
    },
    {
      "id": 94,
      "name": "THOMASINE KRISTOFFERSSON",
      "email": "tkristoffersson2l@jigsy.com",
      "address": "6 Loftsgordon Point"
    },
    {
      "id": 95,
      "name": "BRIG SMITHERMAN",
      "email": "bsmitherman2m@foxnews.com",
      "address": "882 Kings Way"
    },
    {
      "id": 96,
      "name": "ZANDRA WETHERED",
      "email": "zwethered2n@de.vu",
      "address": "0481 Tennessee Point"
    },
    {
      "id": 97,
      "name": "LONNI PENTLAND",
      "email": "lpentland2o@icio.us",
      "address": "18225 Laurel Lane"
    },
    {
      "id": 98,
      "name": "ARLETA HENINGHAM",
      "email": "aheningham2p@dell.com",
      "address": "19631 Meadow Ridge Circle"
    },
    {
      "id": 99,
      "name": "DOY STALEY",
      "email": "dstaley2q@oakley.com",
      "address": "4098 Reinke Place"
    },
    {
      "id": 100,
      "name": "ELOISA PENNOCK",
      "email": "epennock2r@amazon.de",
      "address": "4 Autumn Leaf Point"
    },
    {
      "name": "testName",
      "email": "fgbhdf@dhgd.huf",
      "address": "123123j sedfwewe wefwfw",
      "id": 101
    },
    {
      "name": "testName2",
      "email": "fdh@dhgsd.hu",
      "address": "132 dfefef wsedfwf",
      "id": 103
    },
    {
      "id": 104,
      "name": "testName3",
      "email": "ghjfj@111111",
      "address": "rfjhndfn"
    },
    {
      "name": "test1",
      "email": "erg",
      "address": "egwe",
      "id": 105
    },
    {
      "name": "test2",
      "email": "sdaf@efa",
      "address": "eavds",
      "id": 106
    },
    {
      "name": "NICOLEA LATIMER",
      "email": "nlatimer21@ucoz.ru",
      "address": "191221 Esker Trail",
      "id": 107
    },
    {
      "name": "MILZIE CORBALLY",
      "email": "fnelthorp6@jiathis.co",
      "address": "8 Tban Plaza",
      "id": 108
    },
    {
      "name": "ALVIE ALENDER",
      "email": "agookn@parallels.co",
      "address": "54155 Dahle Crossing",
      "id": 109
    },
    {
      "name": "DEG SDFGG",
      "email": "sgfs@ere.hu",
      "address": "24 Golf Course Avenu",
      "id": 110
    }
  ]
}